README.rst
setup.py
apt_package_mirror/__init__.py
apt_package_mirror/__main__.py
apt_package_mirror/mirror.py
apt_package_mirror.egg-info/PKG-INFO
apt_package_mirror.egg-info/SOURCES.txt
apt_package_mirror.egg-info/dependency_links.txt
apt_package_mirror.egg-info/entry_points.txt
apt_package_mirror.egg-info/requires.txt
apt_package_mirror.egg-info/top_level.txt